dapytains/__init__.py
dapytains/errors.py
dapytains/processor.py
dapytains/app/__init__.py
dapytains/app/app.py
dapytains/app/database.py
dapytains/app/ingest.py
dapytains/app/navigation.py
dapytains/app/transformer.py
dapytains/metadata/__init__.py
dapytains/metadata/classes.py
dapytains/metadata/xml_parser.py
dapytains/tei/__init__.py
dapytains/tei/citeStructure.py
dapytains/tei/document.py
dapytains-0.0.1a4.dist-info/METADATA
dapytains-0.0.1a4.dist-info/WHEEL
dapytains-0.0.1a4.dist-info/top_level.txt
dapytains-0.0.1a4.dist-info/RECORD
