Metadata-Version: 2.4
Name: dapytains
Version: 0.0.1a4
Summary: A brief description of dapytains
Home-page: https://github.com/distributed-text-services/MyDapytains
Author: Thibault Clérice
Author-email: thibault.clerice@inria.fr
Classifier: Programming Language :: Python :: 3
Classifier: License :: OSI Approved :: MIT License
Classifier: Operating System :: OS Independent
Requires-Python: >=3.9
Requires-Dist: saxonche==12.8.0
Requires-Dist: lxml
Requires-Dist: flask
Requires-Dist: flask-sqlalchemy
Requires-Dist: click
Requires-Dist: uritemplate
Requires-Dist: tqdm
Requires-Dist: dotenv_flow
Requires-Dist: waitress
Dynamic: author
Dynamic: author-email
Dynamic: classifier
Dynamic: description
Dynamic: description-content-type
Dynamic: home-page
Dynamic: requires-dist
Dynamic: requires-python
Dynamic: summary
